LICENSE
sidechain_cli/__init__.py
sidechain_cli/bridge/__init__.py
sidechain_cli/bridge/create_account.py
sidechain_cli/bridge/register.py
sidechain_cli/bridge/setup.py
sidechain_cli/bridge/transfer.py
sidechain_cli/exceptions.py
sidechain_cli/main.py
sidechain_cli/misc/__init__.py
sidechain_cli/misc/explorer.html
sidechain_cli/misc/explorer.py
sidechain_cli/misc/fund.py
sidechain_cli/misc/trust.py
sidechain_cli/server/__init__.py
sidechain_cli/server/config/__init__.py
sidechain_cli/server/config/config.py
sidechain_cli/server/config/ports.py
sidechain_cli/server/config/templates/bootstrap.jinja
sidechain_cli/server/config/templates/rippled.jinja
sidechain_cli/server/config/templates/witness.jinja
sidechain_cli/server/list.py
sidechain_cli/server/print.py
sidechain_cli/server/request.py
sidechain_cli/server/restart.py
sidechain_cli/server/start.py
sidechain_cli/server/stop.py
sidechain_cli/utils/__init__.py
sidechain_cli/utils/attestations.py
sidechain_cli/utils/config_file/__init__.py
sidechain_cli/utils/config_file/bridge_config.py
sidechain_cli/utils/config_file/chain_config.py
sidechain_cli/utils/config_file/config_file.py
sidechain_cli/utils/config_file/config_item.py
sidechain_cli/utils/config_file/server_config.py
sidechain_cli/utils/config_file/witness_config.py
sidechain_cli/utils/config_utils.py
sidechain_cli/utils/misc.py
sidechain_cli/utils/rippled_config.py
sidechain_cli/utils/transaction.py
sidechain_cli/utils/types.py
xrpl_sidechain_cli-1.0.0b4.dist-info/entry_points.txt
xrpl_sidechain_cli-1.0.0b4.dist-info/LICENSE
xrpl_sidechain_cli-1.0.0b4.dist-info/WHEEL
xrpl_sidechain_cli-1.0.0b4.dist-info/METADATA
xrpl_sidechain_cli-1.0.0b4.dist-info/RECORD
